MANIFEST.in
README.txt
setup.cfg
setup.py
collective/__init__.py
collective.braveportletsmanager.egg-info/PKG-INFO
collective.braveportletsmanager.egg-info/SOURCES.txt
collective.braveportletsmanager.egg-info/dependency_links.txt
collective.braveportletsmanager.egg-info/entry_points.txt
collective.braveportletsmanager.egg-info/namespace_packages.txt
collective.braveportletsmanager.egg-info/not-zip-safe
collective.braveportletsmanager.egg-info/requires.txt
collective.braveportletsmanager.egg-info/top_level.txt
collective/braveportletsmanager/__init__.py
collective/braveportletsmanager/configure.zcml
collective/braveportletsmanager/overrides.zcml
collective/braveportletsmanager/retriever.py
collective/braveportletsmanager/util.py
collective/braveportletsmanager/browser/__init__.py
collective/braveportletsmanager/browser/configure.zcml
collective/braveportletsmanager/browser/editmanager.py
collective/braveportletsmanager/browser/interfaces.py
collective/braveportletsmanager/browser/kss.py
collective/braveportletsmanager/profiles/default/browserlayer.xml
collective/braveportletsmanager/profiles/default/metadata.xml
docs/HISTORY.txt
docs/INSTALL.txt
docs/LICENSE.GPL
docs/LICENSE.txt