Metadata-Version: 1.1
Name: collective.braveportletsmanager
Version: 1.0.1
Summary: Custom Plone Portlets Manager that doesn't break even with broken or not available portlet assignments
Home-page: https://github.com/softformance/collective.braveportletsmanager
Author: SoftFormance
Author-email: contact@softformance.com
License: GPL
Keywords: plone portlet brave
Platform: UNKNOWN
Classifier: Framework :: Plone
Classifier: Programming Language :: Python
